CHANGES.rst
CONTRIBUTORS.rst
MANIFEST.in
README.rst
setup.cfg
setup.py
docs/LICENSE.GPL
docs/LICENSE.rst
docs/index.rst
src/redturtle/__init__.py
src/redturtle.jquerybrowser.egg-info/PKG-INFO
src/redturtle.jquerybrowser.egg-info/SOURCES.txt
src/redturtle.jquerybrowser.egg-info/dependency_links.txt
src/redturtle.jquerybrowser.egg-info/entry_points.txt
src/redturtle.jquerybrowser.egg-info/namespace_packages.txt
src/redturtle.jquerybrowser.egg-info/not-zip-safe
src/redturtle.jquerybrowser.egg-info/requires.txt
src/redturtle.jquerybrowser.egg-info/top_level.txt
src/redturtle/jquerybrowser/__init__.py
src/redturtle/jquerybrowser/configure.zcml
src/redturtle/jquerybrowser/interfaces.py
src/redturtle/jquerybrowser/setuphandlers.py
src/redturtle/jquerybrowser/testing.py
src/redturtle/jquerybrowser/browser/__init__.py
src/redturtle/jquerybrowser/browser/configure.zcml
src/redturtle/jquerybrowser/browser/static/.gitkeep
src/redturtle/jquerybrowser/browser/static/jquery.browser.min.js
src/redturtle/jquerybrowser/locales/redturtle.jquerybrowser.pot
src/redturtle/jquerybrowser/locales/update.sh
src/redturtle/jquerybrowser/profiles/default/browserlayer.xml
src/redturtle/jquerybrowser/profiles/default/jsregistry.xml
src/redturtle/jquerybrowser/profiles/default/metadata.xml
src/redturtle/jquerybrowser/profiles/default/redturtlejquerybrowser_default.txt
src/redturtle/jquerybrowser/tests/__init__.py
src/redturtle/jquerybrowser/tests/test_robot.py
src/redturtle/jquerybrowser/tests/test_setup.py
src/redturtle/jquerybrowser/tests/robot/test_example.robot