Metadata-Version: 1.1
Name: redturtle.jquerybrowser
Version: 1.0a1
Summary: Add-on for Plone which implements the original jquery-browser code.
Home-page: https://pypi.python.org/pypi/redturtle.jquerybrowser
Author: RedTurtle Technology
Author-email: sviluppoplone@redturtle.it
License: GPL version 2
Keywords: Python Plone
Platform: UNKNOWN
Classifier: Environment :: Web Environment
Classifier: Framework :: Plone
Classifier: Framework :: Plone :: 4.3
Classifier: Programming Language :: Python
Classifier: Programming Language :: Python :: 2.7
Classifier: Operating System :: OS Independent
Classifier: License :: OSI Approved :: GNU General Public License v2 (GPLv2)
